appcannon/__init__.py
appcannon/appcannon.py
appcannon-0.1.0.dist-info/METADATA
appcannon-0.1.0.dist-info/WHEEL
appcannon-0.1.0.dist-info/entry_points.txt
appcannon-0.1.0.dist-info/top_level.txt
appcannon-0.1.0.dist-info/RECORD
