Metadata-Version: 2.1
Name: appcannon
Version: 0.1.0
Summary: AI-powered app generation CLI tool
Home-page: https://github.com/255BITS/appcannon
Author: 255BITS
Author-email: info@255labs.xyz
Classifier: Programming Language :: Python :: 3
Classifier: License :: OSI Approved :: MIT License
Classifier: Operating System :: OS Independent
Requires-Python: >=3.7
Requires-Dist: openai >=1.0.0
Requires-Dist: anthropic >=0.6.0
